[
    {
        "content": "<p>Hi, I'm participating in GCI 2019. The 3d modeling tasks sound really interesting to me.</p>",
        "id": 182377374,
        "sender_full_name": "Chiranjiv Singh Malhi",
        "timestamp": 1575313099
    },
    {
        "content": "<p>welcome <span class=\"user-mention\" data-user-id=\"252403\">@Chiranjiv Singh Malhi</span>!  Do you know what you're going to model first?</p>",
        "id": 182377394,
        "sender_full_name": "Sean",
        "timestamp": 1575313124
    },
    {
        "content": "<p><span class=\"user-mention\" data-user-id=\"102902\">@Sean</span>  Not yet decided but will soon:)</p>",
        "id": 182377846,
        "sender_full_name": "Chiranjiv Singh Malhi",
        "timestamp": 1575313396
    },
    {
        "content": "<p>I recommend going through the three tutorial tasks first, then maybe try the chessboard matrix task</p>",
        "id": 182377899,
        "sender_full_name": "Sean",
        "timestamp": 1575313434
    },
    {
        "content": "<p>Thank you for the advice <span class=\"user-mention\" data-user-id=\"102902\">@Sean</span></p>",
        "id": 182377998,
        "sender_full_name": "Chiranjiv Singh Malhi",
        "timestamp": 1575313503
    },
    {
        "content": "<p><span class=\"user-mention\" data-user-id=\"103539\">@Oleksandr Dubenko</span> great!  thx for noticing and even more for fixing them!</p>",
        "id": 182382518,
        "sender_full_name": "Sean",
        "timestamp": 1575316350
    }
]