[
    {
        "content": "<p>Hey <span class=\"user-mention\" data-user-id=\"102939\">@Daniel Rossberg</span> I completed the task RUN A CODE QUALITY ASSESSMENT ON OGV USING CODECLIMATE and submit for review.</p>",
        "id": 184810705,
        "sender_full_name": "Thusal Ranawaka",
        "timestamp": 1578155554
    },
    {
        "content": "<p>Time to bed. Good night !</p>",
        "id": 184810851,
        "sender_full_name": "Thusal Ranawaka",
        "timestamp": 1578155837
    },
    {
        "content": "<blockquote>\n<p>Hey <span class=\"user-mention silent\" data-user-id=\"102939\">Daniel Rossberg</span> I completed the task RUN A CODE QUALITY ASSESSMENT ON OGV USING CODECLIMATE and submit for review.</p>\n</blockquote>\n<p>And, you found out how to do it by yourself <span aria-label=\"+1\" class=\"emoji emoji-1f44d\" role=\"img\" title=\"+1\">:+1:</span></p>",
        "id": 184811023,
        "sender_full_name": "Daniel Rossberg",
        "timestamp": 1578156129
    }
]