[
    {
        "content": "<p><span class=\"user-mention\" data-user-email=\"mikehanus@protonmail.com\" data-user-id=\"104130\">@Michal Hanus</span> do you still have access to all the work you did in GCI 2016?  if you can find all your work, I'd love to get a copy of all the files .. I have a some of the data, but some files were unfortunately lost</p>",
        "id": 121865742,
        "sender_full_name": "Sean",
        "timestamp": 1517462095
    },
    {
        "content": "<p>your list of tasks: <a href=\"https://codein.withgoogle.com/archive/search/?q=Michal%20Hanus\" target=\"_blank\" title=\"https://codein.withgoogle.com/archive/search/?q=Michal%20Hanus\">https://codein.withgoogle.com/archive/search/?q=Michal%20Hanus</a></p>",
        "id": 121865791,
        "sender_full_name": "Sean",
        "timestamp": 1517462174
    }
]